mylib_046/__init__.py
mylib_046-0.1.dist-info/LICENSE.txt
mylib_046-0.1.dist-info/METADATA
mylib_046-0.1.dist-info/WHEEL
mylib_046-0.1.dist-info/top_level.txt
mylib_046-0.1.dist-info/RECORD
