Metadata-Version: 2.1
Name: mylib-046
Version: 0.1
Summary: Greet to a Person
Home-page: UNKNOWN
Author: Suraj
Author-email: srjpatil489@gmail.com
License: UNKNOWN
Platform: UNKNOWN
Classifier: Programming Language :: Python :: 3
Classifier: License :: OSI Approved :: MIT License
Classifier: Operating System :: OS Independent
